pyibl.py
pyibl-5.2.2.dist-info/LICENSE.txt
pyibl-5.2.2.dist-info/METADATA
pyibl-5.2.2.dist-info/WHEEL
pyibl-5.2.2.dist-info/top_level.txt
pyibl-5.2.2.dist-info/RECORD
