Metadata-Version: 2.1
Name: pyibl
Version: 5.2.2
Summary: A Python implementation of a subset of Instance Based Learning Theory
Home-page: https://ddm-lab.github.io/pyibl-documentation/
Author: Dynamic Decision Making Laboratory of Carnegie Mellon University
Author-email: dfm2@cmu.edu
License: Free for research purposes
Platform: any
Classifier: Intended Audience :: Science/Research
Classifier: License :: OSI Approved :: MIT License
Classifier: Programming Language :: Python
Classifier: Programming Language :: Python :: 3 :: Only
Classifier: Programming Language :: Python :: 3.8
Classifier: Programming Language :: Python :: 3.9
Classifier: Programming Language :: Python :: 3.10
Classifier: Programming Language :: Python :: 3.11
Classifier: Operating System :: OS Independent
Requires-Python: >=3.8
License-File: LICENSE.txt
Requires-Dist: matplotlib
Requires-Dist: ordered-set
Requires-Dist: packaging
Requires-Dist: pandas
Requires-Dist: prettytable
Requires-Dist: pyactup >=2.2.3
